ogapiPy/__init__.py
ogapiPy/opengate_client.py
ogapiPy/ai_models/__init__.py
ogapiPy/ai_models/ai_models.py
ogapiPy/ai_pipelines/__init__.py
ogapiPy/ai_pipelines/ai_pipelines.py
ogapiPy/ai_transformers/__init__.py
ogapiPy/ai_transformers/ai_transformers.py
ogapiPy/datapoints/__init__.py
ogapiPy/datapoints/datapoints.py
ogapiPy/datasets/__init__.py
ogapiPy/datasets/datasets.py
ogapiPy/entities/__init__.py
ogapiPy/entities/entities.py
ogapiPy/rules/__init__.py
ogapiPy/rules/rules.py
ogapiPy/test/__init__.py
ogapiPy/test/ownworld.py
ogapiPy/test/test_steps_cucumber.py
ogapiPy/timeseries/__init__.py
ogapiPy/timeseries/timeseries.py
ogapiPy-1.0.4.dist-info/METADATA
ogapiPy-1.0.4.dist-info/WHEEL
ogapiPy-1.0.4.dist-info/top_level.txt
ogapiPy-1.0.4.dist-info/RECORD
