Metadata-Version: 2.1
Name: ogapiPy
Version: 1.0.4
Summary: Description
Author: manuel haro fulgencio
Author-email: manuel.haro@amplia.es
License: Apache License 2.0
Requires-Dist: pandas
Requires-Dist: requests
Requires-Dist: jsonpath-ng
Requires-Dist: numpy
Requires-Dist: urllib3
Requires-Dist: configparser
Requires-Dist: parse
Requires-Dist: python-dotenv
